Nictk/__init__.py
Nictk/constants.py
Nictk-2.2.0.dist-info/COPYING
Nictk-2.2.0.dist-info/COPYING.LESSER
Nictk-2.2.0.dist-info/METADATA
Nictk-2.2.0.dist-info/WHEEL
Nictk-2.2.0.dist-info/top_level.txt
Nictk-2.2.0.dist-info/RECORD
