Metadata-Version: 2.1
Name: Nictk
Version: 2.2.0
Summary: An easy to use GUI for Python
Home-page: https://github.com/ncassetta/Nictk
Author: Nicola Cassetta
Author-email: Nicola Cassetta <ncassetta@tiscali.it>
Project-URL: Homepage, https://github.com/ncassetta/Nictk
Project-URL: Documentation, https://ncassetta.github.io/Nictk/docs/html/
Keywords: GUI,tkinter,graphic :: interface
Classifier: Programming Language :: Python :: 3
Classifier: License :: OSI Approved :: GNU Lesser General Public License v3 (LGPLv3)
Classifier: Operating System :: OS Independent
Requires-Python: >=3.6
License-File: COPYING
License-File: COPYING.LESSER
